{
  "logo": {
    "text": "GANESH TAX",
    "icon": "⚖️",
    "url": "/assets/ganeshTaxLogo.png"
  },
  "navigation": [
    {
      "label": "Home",
      "href": "/",
      "id": "home",
      "subLinks": []
    },
    {
      "label": "Start a Business",
      "href": "/start-a-business",
      "type": "category",
      "id": "start-a-business",
      "subLinks": [
        {
          "label": "Private Limited (Pvt Ltd) Company Registration in India",
          "href": "/start-a-business/private-limited-company-registration-in-india",
          "id": "private-limited-company-registration-in-india"
        },
        {
          "label": "Limited liability registration",
          "href": "/start-a-business/limited-liability-registration",
          "id": "limited-liability-registration"
        },
        {
          "label": "Sole Proprietorship Firm Registration",
          "href": "/start-a-business/sole-proprietorship-firm-registration",
          "id": "sole-proprietorship-firm-registration"
        },
        {
          "label": "Partnership firm registration",
          "href": "/start-a-business/partnership-firm-registration",
          "id": "partnership-firm-registration"
        }
      ]
    },
    {
      "label": "Registrations",
      "href": "/registrations",
      "type": "category",
      "id": "registrations",
      "subLinks": [
        {
          "label": "MSME registration",
          "href": "/registrations/msme-registration",
          "id": "msme-registration"
        },
        {
          "label": "Drug licences",
          "href": "/registrations/drug-licences",
          "id": "drug-licences"
        },
        {
          "label": "Digital Signature Certificate (DSC)",
          "href": "/registrations/digital-signature-certificate",
          "id": "digital-signature-certificate"
        },
        {
          "label": "12A and 80G Registration",
          "href": "/registrations/12A-and-80G-registration",
          "id": "12A-and-80G-registration"
        },
        {
          "label": "IEC Certification",
          "href": "/registrations/iec-certification",
          "id": "iec-certification"
        },
        {
          "label": "PF Registration",
          "href": "/registrations/pf-registration",
          "id": "pf-registration"
        },
        {
          "label": "ESI Registration",
          "href": "/registrations/esi-registration",
          "id": "esi-registration"
        },
        {
          "label": "Professional Tax Registration",
          "href": "/registrations/professional-tax-registration",
          "id": "professional-tax-registration"
        }
      ]
    },
   
    {
      "label": "Income Tax eFiling",
      "href": "/income-tax-eFiling",
      "type": "category",
      "id": "income-tax-eFiling",
      "subLinks": [
        {
          "label": "Income Tax filing",
          "href": "/income-tax-eFiling/income-tax-filing",
          "id": "income-tax-filing"
        },
        {
          "label": "Business Income Tax Return",
          "href": "/income-tax-eFiling/business-income-tax-return",
          "id": "business-income-tax-return"
        }
      ]
    },
 

    {
      "label": "Contact",
      "href": "/contact",
      "id": "contact",
      "subLinks": []
    }
  ],
  "cta": {
    "text": "Get Started",
    "href": "/contact",
    "variant": "default"
  }
}
